[
  {
    "college" : "東北大学",
    "name"    : "総合技術研究会2021東北大学",
    "date"    : "2021年3月3日(水)~5日(金)",
    "url"     : "URL"
  },
  {
    "college" : "奈良先端科学技術大学院大学",
    "name"    : "2020年度機器・分析技術研究会",
    "date"    : "2020年9月10日(木)11日(金)",
    "url"     : "URL"
  },
  {
    "college" : "鹿児島大学",
    "name"    : "実験・実習技術研究会2020 鹿児島大学",
    "date"    : "2020年3月18日(水)19日(木)",
    "url"     : "URL"
  },
  {
    "college" : "東京大学",
    "name"    : "第3回東京大学技術発表会",
    "date"    : "2020年3月12日(木)13日(金)",
    "url"     : "URL"
  },
  {
    "college" : "千葉大学",
    "name"    : "2020年度技術研究会",
    "date"    : "2020年3月5日(木)6日(金)",
    "url"     : "URL"
  },
  {
    "college" : "九州工業大学",
    "name"    : "第1回 機械工作技術研究会",
    "date"    : "2019年9月19日(木)20日(金)",
    "url"     : "URL"
  }
]